thoth/tasks/__init__.py
thoth_tasks-0.0.0.dist-info/DESCRIPTION.rst
thoth_tasks-0.0.0.dist-info/METADATA
thoth_tasks-0.0.0.dist-info/RECORD
thoth_tasks-0.0.0.dist-info/WHEEL
thoth_tasks-0.0.0.dist-info/metadata.json
thoth_tasks-0.0.0.dist-info/top_level.txt
