Metadata-Version: 2.0
Name: thoth-tasks
Version: 0.0.0
Summary: Tasks available in project Thoth
Home-page: UNKNOWN
Author: Fridolin Pokorny
Author-email: fridolin@redhat.com
License: GPLv2+
Platform: UNKNOWN
